gphl.cp38-win_amd64.pyd
gphl-0.1.4.dist-info/METADATA
gphl-0.1.4.dist-info/WHEEL
gphl-0.1.4.dist-info/licenses/LICENSE
gphl-0.1.4.dist-info/RECORD
