Metadata-Version: 2.2
Name: gphl
Version: 0.1.4
Summary: A C++ graph library with Python bindings.
License: MIT
Classifier: Programming Language :: Python :: 3
Classifier: Programming Language :: C++
Classifier: Operating System :: OS Independent
